README.md
setup.cfg
setup.py
pyfranca/__init__.py
pyfranca/ast.py
pyfranca/franca_lexer.py
pyfranca/franca_parser.py
pyfranca/franca_processor.py
pyfranca.egg-info/PKG-INFO
pyfranca.egg-info/SOURCES.txt
pyfranca.egg-info/dependency_links.txt
pyfranca.egg-info/requires.txt
pyfranca.egg-info/top_level.txt
pyfranca/tests/__init__.py
pyfranca/tests/test_franca_lexer.py
pyfranca/tests/test_franca_parser.py
pyfranca/tests/test_franca_processor.py
tools/fidl_dump.py
tools/fidl_validator.py