Metadata-Version: 1.1
Name: pyfranca
Version: 0.4.1
Summary: Python parser and tools for working with the Franca interface definition language.
Home-page: http://github.com/zayfod/pyfranca
Author: Kaloyan Tenchov
Author-email: zayfod@gmail.com
License: MIT
Download-URL: https://github.com/zayfod/pyfranca/archive/0.4.1.zip
Keywords: franca,franca-idl,idl,fidl,parsing
Platform: Python 2.7 or 3.4 .
